outlier_cleaner/__init__.py
outlier_cleaner/cleaner.py
outlier_cleaner/utils.py
outlier_cleaner-1.1.4.dist-info/licenses/LICENSE
tests/__init__.py
tests/test_outlier_cleaner.py
outlier_cleaner-1.1.4.dist-info/METADATA
outlier_cleaner-1.1.4.dist-info/WHEEL
outlier_cleaner-1.1.4.dist-info/top_level.txt
outlier_cleaner-1.1.4.dist-info/RECORD
