Metadata-Version: 2.4
Name: outlier_cleaner
Version: 1.1.4
Summary: A Python package for detecting and removing outliers in data using various statistical methods and advanced distribution analysis
Home-page: https://github.com/SubaashNair/OutlierCleaner
Author: Subashanan Nair
Author-email: subaashnair12@gmail.com
Project-URL: Homepage, https://github.com/SubaashNair/OutlierCleaner
Project-URL: Source, https://github.com/SubaashNair/OutlierCleaner
Project-URL: Tracker, https://github.com/SubaashNair/OutlierCleaner/issues
Project-URL: Documentation, https://github.com/SubaashNair/OutlierCleaner#readme
Classifier: Development Status :: 5 - Production/Stable
Classifier: Intended Audience :: Science/Research
Classifier: License :: OSI Approved :: MIT License
Classifier: Operating System :: OS Independent
Classifier: Programming Language :: Python :: 3
Classifier: Programming Language :: Python :: 3.7
Classifier: Programming Language :: Python :: 3.8
Classifier: Programming Language :: Python :: 3.9
Classifier: Programming Language :: Python :: 3.10
Classifier: Topic :: Scientific/Engineering :: Information Analysis
Classifier: Topic :: Scientific/Engineering :: Mathematics
Classifier: Topic :: Software Development :: Libraries :: Python Modules
Requires-Python: >=3.7
License-File: LICENSE
Requires-Dist: numpy>=1.19.0
Requires-Dist: pandas>=1.2.0
Requires-Dist: matplotlib>=3.3.0
Requires-Dist: seaborn>=0.11.0
Requires-Dist: scipy>=1.6.0
Requires-Dist: tqdm>=4.60.0
Dynamic: author
Dynamic: author-email
Dynamic: classifier
Dynamic: description
Dynamic: description-content-type
Dynamic: home-page
Dynamic: license-file
Dynamic: project-url
Dynamic: requires-dist
Dynamic: requires-python
Dynamic: summary
